ABCENTH/ABCENTH-legacy.py
ABCENTH/FindOrfs.py
ABCENTH/HitTabFilter.py
ABCENTH/ParseHAPpyTable.py
ABCENTH/__init__.py
ABCENTH/__main__.py
HAPpy/AnnotatorRunner.py
HAPpy/CandidateLociBuilder.py
HAPpy/HAPpy-hiMem-client.py
HAPpy/__init__.py
HAPpy/__main__.py
HAPpy/genome_fork.py
HAPpy/thammerin.py
HAPpy/toolbox_for_HAP.py
HAPpy/cfgFiles/BLOSUM30.bla
HAPpy/cfgFiles/BLOSUM45.bla
HAPpy/cfgFiles/BLOSUM62.bla
HAPpy/cfgFiles/BLOSUM80.bla
HAPpy/cfgFiles/aa.rnd
HAPpy/cfgFiles/augustus_extrinsic.MP.cfg
HAPpy/cfgFiles/cb.tmf
HAPpy/cfgFiles/codon.martian
HAPpy/cfgFiles/codon.table
HAPpy/cfgFiles/gene.stat
HAPpy/cfgFiles/gon120.bla
HAPpy/cfgFiles/gon160.bla
HAPpy/cfgFiles/gon200.bla
HAPpy/cfgFiles/gon250.bla
HAPpy/cfgFiles/gon350.bla
HAPpy/cfgFiles/human.gf
HAPpy/cfgFiles/human.gp
HAPpy/cfgFiles/human.stats
HAPpy/cfgFiles/idenity.bla
HAPpy/cfgFiles/methods
HAPpy/cfgFiles/pb.gf
HAPpy/cfgFiles/pombe.gf
HAPpy/cfgFiles/spliceAG.txt
HAPpy/cfgFiles/spliceGT.txt
HAPpy/cfgFiles/tm.pri
HAPpy/cfgFiles/wag55
HAPpy/cfgFiles/wag65
HAPpy/cfgFiles/wag75
HAPpy/cfgFiles/wag85
HAPpy/cfgFiles/wise.2
HAPpy/cfgFiles/wise.per
HAPpy/cfgFiles/worm.gf
HAPpy_ABCENTH-1.0.2.dist-info/LICENSE
HAPpy_ABCENTH-1.0.2.dist-info/METADATA
HAPpy_ABCENTH-1.0.2.dist-info/WHEEL
HAPpy_ABCENTH-1.0.2.dist-info/entry_points.txt
HAPpy_ABCENTH-1.0.2.dist-info/top_level.txt
HAPpy_ABCENTH-1.0.2.dist-info/RECORD
