Metadata-Version: 2.1
Name: HAPpy-ABCENTH
Version: 1.0.2
Summary: UNKNOWN
Home-page: UNKNOWN
License: UNKNOWN
Platform: UNKNOWN
License-File: LICENSE
Requires-Dist: ete3
Requires-Dist: numpy
Requires-Dist: intervaltree
